ai_sar_2024/__init__.py
ai_sar_2024/ai_sar_2024.py
ai_sar_2024-1.0.dist-info/LICENSE.txt
ai_sar_2024-1.0.dist-info/METADATA
ai_sar_2024-1.0.dist-info/WHEEL
ai_sar_2024-1.0.dist-info/top_level.txt
ai_sar_2024-1.0.dist-info/RECORD
