Metadata-Version: 2.1
Name: ai_sar_2024
Version: 1.0
Summary: Just a simple AI tool for daily simple tasks by Shubham Anand Rashmi - powered by MetaAI
Author: Shubham
Author-email: Shub76ham@gmail.com
License: MIT
Project-URL: Source Repository, https://github.com/Sm7-git/
License-File: LICENSE.txt
Requires-Dist: meta-ai-api
